s3synchrony/BasePlatform.py
s3synchrony/__init__.py
s3synchrony/__main__.py
s3synchrony/s3synchrony_main.py
s3synchrony/s3synchrony_template.json
s3synchrony/Platforms/__init__.py
s3synchrony/Platforms/s3.py
s3synchrony/Templates/__init__.py
s3synchrony/Templates/default.py
s3synchrony/Templates/no_creds_needed.py
kabbes_s3synchrony-0.4.0.dist-info/LICENSE.md
kabbes_s3synchrony-0.4.0.dist-info/METADATA
kabbes_s3synchrony-0.4.0.dist-info/WHEEL
kabbes_s3synchrony-0.4.0.dist-info/top_level.txt
kabbes_s3synchrony-0.4.0.dist-info/RECORD
