Metadata-Version: 2.1
Name: kabbes-s3synchrony
Version: 0.4.0
Summary: S3 File synchronization service
Home-page: https://pypi.org/project/kabbes-s3synchrony/
Author: James Kabbes
Author-email: james.kabbes@gmail.com
Project-URL: GitHub, https://github.com/jameskabbes/s3synchrony
Project-URL: Documentation, https://jameskabbes.github.io/s3synchrony
Classifier: Programming Language :: Python :: 3
Classifier: License :: OSI Approved :: MIT License
Classifier: Operating System :: OS Independent
Requires-Python: >=3.7
License-File: LICENSE.md
Requires-Dist: kabbes-py-starter
Requires-Dist: kabbes-parent-class
Requires-Dist: kabbes-dir-ops
Requires-Dist: kabbes-aws-credentials
Requires-Dist: boto3
